<?xml version="1.0" encoding="utf-8"?>
<!DOCTYPE hibernate-mapping PUBLIC "-//Hibernate/Hibernate Mapping DTD 3.0//EN"
"http://www.hibernate.org/dtd/hibernate-mapping-3.0.dtd">
<!-- 
    Mapping file autogenerated by MyEclipse Persistence Tools
-->
<hibernate-mapping>
    <class name="com.agjsj.entity.Resume" table="resume" catalog="drip">
        <id name="resumeId" type="java.lang.Integer">
            <column name="Resume_id" />
            <generator class="native"></generator>
        </id>
        <property name="userId" type="java.lang.Integer">
            <column name="User_id" not-null="true" />
        </property>
        <property name="resumeName" type="java.lang.String">
            <column name="Resume_name" length="10" not-null="true" />
        </property>
         <property name="resumeSex" type="java.lang.Integer">
            <column name="Resume_sex"  not-null="true" />
        </property>
        <property name="resumeAge" type="java.lang.Integer">
            <column name="Resume_age"  not-null="true" />
        </property>
        <property name="resumeNation" type="java.lang.String">
            <column name="Resume_nation" length="5" not-null="true" />
        </property>
        <property name="resumeStatus" type="java.lang.String">
            <column name="Resume_status" length="10" not-null="true" />
        </property>
        <property name="resumePlace" type="java.lang.String">
            <column name="Resume_place" length="50" not-null="true" />
        </property>
        <property name="resumeSchool" type="java.lang.String">
            <column name="Resume_school" length="20" not-null="true" />
        </property>
        <property name="resumeMajor" type="java.lang.String">
            <column name="Resume_major" length="20" not-null="true" />
        </property>
        <property name="resumeEducation" type="java.lang.String">
            <column name="Resume_education" length="20" not-null="true" />
        </property>
        <property name="resumeIntention" type="java.lang.String">
            <column name="Resume_intention" length="50" not-null="true" />
        </property>
        <property name="resumePhone" type="java.lang.String">
            <column name="Resume_phone" length="11" not-null="true" />
        </property>
        <property name="resumeEmail" type="java.lang.String">
            <column name="Resume_email" length="20" not-null="true" />
        </property>
        <property name="resumeAddress" type="java.lang.String">
            <column name="Resume_address" length="50" not-null="true" />
        </property>
        <property name="resumeStrong" type="java.lang.String">
            <column name="Resume_strong" length="65535" not-null="true" />
        </property>
        <property name="resumeHonor" type="java.lang.String">
            <column name="Resume_honor" length="65535" not-null="true" />
        </property>
        <property name="resumeExperience" type="java.lang.String">
            <column name="Resume_experience" length="65535" not-null="true" />
        </property>
        <property name="resumeMyevaluate" type="java.lang.String">
            <column name="Resume_myevaluate" length="65535" not-null="true" />
        </property>
    </class>
</hibernate-mapping>
